setup.py
lgr/__init__.py
lgr/utils.py
liuguangrui.egg-info/PKG-INFO
liuguangrui.egg-info/SOURCES.txt
liuguangrui.egg-info/dependency_links.txt
liuguangrui.egg-info/not-zip-safe
liuguangrui.egg-info/top_level.txt