Metadata-Version: 1.0
Name: liuguangrui
Version: 0.1
Summary: test1
Home-page: UNKNOWN
Author: liuguangrui
Author-email: 18302465887@163.com
License: UNKNOWN
Platform: UNKNOWN
